[{"id":"ad473cd6-fae7-4f3e-b5e8-d847554f8e92","name":"John1 Doe","email":"john.do1e@example.com","password":"$2a$10$6aOZ8.xRbWsyTOa5XMIVVuf.54qUsvbZnKweq5AlYIlseyr8Cw6d.","collections":[]},{"id":"45865acf-034d-4e51-8538-0f43f08f5c7b","name":"John11 Doe","email":"john1.do1e@example.com","password":"$2a$10$8eRj1hwgfnKzwoB.imvsg.VlmHZXTu7L1Hy3AsaavU5tt5Ckk.Bmy","collections":[]},{"id":"6cb945cf-b454-4571-a3b0-0dd0e1e530d0","name":"John111 Doe","email":"john11.do1e@example.com","password":"$2a$10$hev.tQ1nydsjDc5CIZh1t.E8ARyiuoWJNdTgOwXorqenmuquerq6S","collections":[],"registrationDate":"2024-05-23T09:46:04.035Z"},{"id":"3f4f3d31-e984-4df4-94f9-742f2bee0bba","name":"John1111 Doe","email":"john111.do1e@example.com","password":"$2a$10$vxWX/ZBgeSCY0gDtOo/zW.zaIxB5nUTpbM.S4txGtD.rt7Qlejkje","collections":[],"registrationDate":"2024-05-23T17:40:08.731Z"},{"id":"0d136c5d-fdb5-4db0-a9cd-2ec1d6181737","name":"John11111 Doe","email":"john1111.do1e@example.com","password":"$2a$10$CUT4ZVyulodmjSsQUa1.FO7r1b5pQZhG0fi1TF/HtXWqzjy2llOo.","collections":[],"registrationDate":"2024-05-23T17:46:32.552Z"},{"id":"14eefe81-30a0-47c5-bc90-63de34e3e699","name":"1","email":"makspala777@gmail.com","password":"$2a$10$iq8HGLxj9nwDV1Po4cpKne58f6Z26YQ67ltlnst1OcGBGGxN2qgca","collections":[],"registrationDate":"2024-05-23T18:42:26.178Z"},{"id":"7356e5db-bccd-401c-88b1-207d696a1731","name":"user1@example.com","email":"user1@example.com","password":"$2a$10$Wi.nctriPKjQLSCxdltZg.RaIrXe1zq36HNANFmXvExU.jAV5WnIq","collections":[],"registrationDate":"2024-05-29T19:13:22.139Z"},{"id":"96f284ea-1618-444e-8fe6-93c75a8c50f4","name":"Vitae","email":"makspala7771@gmail.com","password":"$2a$10$UswNsdPzgRizkjDSw6GEMOBTYCZh.b3ftt/QxWx55EEWH/4vr1mtS","collections":[],"registrationDate":"2024-05-30T14:25:01.608Z"}]
